{
    "interactionModel": {
        "languageModel": {
            "invocationName": "simple barkeeper",
            "intents": [
                {
                    "name": "CancelIntent",
                    "slots": [],
                    "samples": []
                },
                {
                    "name": "AMAZON.HelpIntent",
                    "samples": []
                },
                {
                    "name": "StopIntent",
                    "slots": [],
                    "samples": [
                        "Beende Anwendung",
                        "Ich will doch keinen Drink"
                    ]
                }
            ],
            "types": []
        }
    }
}